airflow_multi_dagrun/__init__.py
airflow_multi_dagrun/operators.py
airflow_multi_dagrun/sensors.py
airflow_multi_dagrun/utils.py
airflow_multi_dagrun-2.3.1.dist-info/LICENSE
airflow_multi_dagrun-2.3.1.dist-info/METADATA
airflow_multi_dagrun-2.3.1.dist-info/WHEEL
airflow_multi_dagrun-2.3.1.dist-info/entry_points.txt
airflow_multi_dagrun-2.3.1.dist-info/top_level.txt
airflow_multi_dagrun-2.3.1.dist-info/RECORD
