Metadata-Version: 2.1
Name: airflow-multi-dagrun
Version: 2.3.1
Summary: MultiDagRunPlugin for airflow
Home-page: https://github.com/mastak/airflow_multi_dagrun
Author: Ihor Liubymov
Author-email: infunt@gmail.com
License: UNKNOWN
Platform: UNKNOWN
Requires-Python: >=3.6.0
